kelvin/sdk/client/__init__.py
kelvin/sdk/client/base_client.py
kelvin/sdk/client/base_model.py
kelvin/sdk/client/client.py
kelvin/sdk/client/config.py
kelvin/sdk/client/data_model.py
kelvin/sdk/client/deeplist.py
kelvin/sdk/client/error.py
kelvin/sdk/client/io.py
kelvin/sdk/client/magic.py
kelvin/sdk/client/py.typed
kelvin/sdk/client/retry.py
kelvin/sdk/client/serialize.py
kelvin/sdk/client/utils.py
kelvin/sdk/client/version.py
kelvin/sdk/client/model/__init__.py
kelvin/sdk/client/model/domain.py
kelvin/sdk/client/model/errors.py
kelvin/sdk/client/model/kerrors.py
kelvin/sdk/client/model/models.py
kelvin/sdk/client/model/pagination.py
kelvin/sdk/client/model/paginator.py
kelvin/sdk/client/model/parameterschema.py
kelvin/sdk/client/model/requests.py
kelvin/sdk/client/model/responses.py
kelvin/sdk/client/model/utils.py
kelvin_sdk_client-8.1.0.dist-info/METADATA
kelvin_sdk_client-8.1.0.dist-info/WHEEL
kelvin_sdk_client-8.1.0.dist-info/top_level.txt
kelvin_sdk_client-8.1.0.dist-info/RECORD
