Metadata-Version: 2.1
Name: kelvin-sdk-client
Version: 8.1.0
Summary: Kelvin API Client
Home-page: https://kelvininc.com/
Author: Kelvin Inc
Author-email: engineering@kelvininc.com
Platform: any
Classifier: Operating System :: OS Independent
Classifier: Programming Language :: Python :: 3
Requires-Python: >=3.8.0
Requires-Dist: PyJWT==2.9.*
Requires-Dist: PyYAML==6.0.*
Requires-Dist: Jinja2==3.1.*
Requires-Dist: keyring==24.1.*
Requires-Dist: keyrings.alt==5.*
Requires-Dist: filelock==3.16.*
Requires-Dist: pydantic[email]==2.*
Requires-Dist: python-keycloak==3.6.*
Requires-Dist: requests==2.32.*
Requires-Dist: ruamel.yaml==0.18.*
Requires-Dist: structlog==23.1.*
Requires-Dist: typing-inspect==0.9.*
Requires-Dist: tzlocal==5.2.*
Requires-Dist: websockets==13.*
Requires-Dist: xdg==6.0.*
Requires-Dist: python-certifi-win32; platform_system == "Windows"
Requires-Dist: typing-extensions; python_version < "3.8"
Provides-Extra: build
Requires-Dist: datamodel-code-generator==0.11.*; extra == "build"
Requires-Dist: prance==0.21.*; extra == "build"
Provides-Extra: development
Requires-Dist: pre-commit; extra == "development"
Provides-Extra: docs
Requires-Dist: Sphinx==4.2.0; extra == "docs"
Requires-Dist: sphinx-autodoc-typehints==1.12.0; extra == "docs"
Requires-Dist: sphinx-rtd-theme==1.0.*; extra == "docs"
Requires-Dist: ipython; extra == "docs"
Provides-Extra: format
Requires-Dist: isort==5.10.*; extra == "format"
Requires-Dist: black==22.3.0; extra == "format"
Provides-Extra: lint
Requires-Dist: flake8==4.0.*; extra == "lint"
Requires-Dist: flake8-print==4.0.*; extra == "lint"
Requires-Dist: flake8-isort==4.1.*; extra == "lint"
Requires-Dist: pep8-naming==0.12.*; extra == "lint"
Requires-Dist: mypy[reports]==1.4.*; extra == "lint"
Requires-Dist: types-filelock==3.2.*; extra == "lint"
Requires-Dist: types-PyYAML==5.4.*; extra == "lint"
Requires-Dist: types-requests==2.25.*; extra == "lint"
Requires-Dist: types-tzlocal==0.1.*; extra == "lint"
Provides-Extra: security
Requires-Dist: bandit==1.7.*; extra == "security"
Requires-Dist: safety==2.2.*,>=2.2.0; extra == "security"
Provides-Extra: tests
Requires-Dist: coverage==6.1.*; extra == "tests"
Requires-Dist: pandas>1.3; extra == "tests"
Requires-Dist: pytest==6.2.*; extra == "tests"
Requires-Dist: pytest-asyncio==0.16.*; extra == "tests"
Requires-Dist: pytest-cov==3.0.*; extra == "tests"
Requires-Dist: pytest-mock==3.6.*; extra == "tests"
Requires-Dist: pytest-benchmark==3.4.*; extra == "tests"
Requires-Dist: pytest-codestyle==2.0.*; extra == "tests"
Requires-Dist: pytest-flakes==4.0.*; extra == "tests"
Requires-Dist: pytest-html==3.1.*; extra == "tests"
Requires-Dist: pytest-mypy==0.8.*; extra == "tests"
Requires-Dist: pytest-timeout==2.0.*; extra == "tests"
Requires-Dist: pytest-xdist==2.4.*; extra == "tests"
Requires-Dist: pytest-virtualenv==1.8.*; extra == "tests"
Requires-Dist: requests-mock==1.9.*; extra == "tests"
Provides-Extra: wheel
Requires-Dist: wheel; extra == "wheel"
Requires-Dist: twine; extra == "wheel"
